{
  "name": "c-barkling-wizard-3",
  "specie": "humanoid",
  "naturalArmorClass": 11,
  "saveAsLevel": "magic-user",
  "level": 1,
  "actions": [
    {
      "name": "bite",
      "count": 1,
      "amp": "1d4",
      "script": "damage",
      "data": []
    },
    {
      "name": "weapon",
      "count": 1,
      "amp": "0",
      "script": "damage",
      "data": []
    },
    {
      "name": "spell",
      "count": 1,
      "amp": "0",
      "script": "damage",
      "data": []
    }
  ],
  "saveAsClass": 20
}