{
  "name": "c-ghast",
  "ac": 15,
  "classType": "CLASS_TYPE_MONSTER",
  "actions": [
    {
      "name": "claw",
      "attackType": "ATTACK_TYPE_MELEE",
      "damage": "1d4",
      "damageType": "DAMAGE_TYPE_PHYSICAL",
      "count": 2,
      "cooldown": 0,
      "conveys": [
        {
          "script": "atk-paralysis",
          "data": {}
        }
      ]
    },
    {
      "name": "bite",
      "attackType": "ATTACK_TYPE_MELEE",
      "damage": "1d4",
      "damageType": "DAMAGE_TYPE_PHYSICAL",
      "count": 1,
      "cooldown": 0,
      "conveys": [
        {
          "script": "atk-paralysis",
          "data": {}
        },
        {
          "script": "atk-disease",
          "data": {
            "disease": "ghoul-fever",
            "chance": 10
          }
        }
      ]
    },
    {
      "name": "stench",
      "attackType": "ATTACK_TYPE_HOMING",
      "damage": 0,
      "damageType": "DAMAGE_TYPE_PHYSICAL",
      "count": 1,
      "cooldown": 0,
      "conveys": [
        {
          "script": "atk-toxic-stench",
          "data": {}
        }
      ]
    }
  ],
  "properties": [
    {
      "property": "ITEM_PROPERTY_IMMUNITY",
      "amp": 0,
      "data": {
        "immunityType": "IMMUNITY_TYPE_PARALYSIS"
      }
    },
    {
      "property": "ITEM_PROPERTY_IMMUNITY",
      "amp": 0,
      "data": {
        "immunityType": "IMMUNITY_TYPE_CHARM"
      }
    },
    {
      "property": "ITEM_PROPERTY_IMMUNITY",
      "amp": 0,
      "data": {
        "immunityType": "IMMUNITY_TYPE_STUN"
      }
    },
    {
      "property": "ITEM_PROPERTY_IMMUNITY",
      "amp": 0,
      "data": {
        "immunityType": "IMMUNITY_TYPE_DAZED"
      }
    },
    {
      "property": "ITEM_PROPERTY_DAMAGE_IMMUNITY",
      "amp": 0,
      "data": {
        "damageType": "DAMAGE_TYPE_POISON"
      }
    },
    {
      "property": "ITEM_PROPERTY_DAMAGE_RESISTANCE",
      "amp": 0,
      "data": {
        "damageType": "DAMAGE_TYPE_NECROTIC"
      }
    }
  ],
  "equipment": [],
  "abilities": {
    "strength": 10,
    "dexterity": 10,
    "constitution": 10,
    "intelligence": 10,
    "wisdom": 10,
    "charisma": 10
  },
  "specie": "SPECIE_UNDEAD",
  "level": 2,
  "speed": 30,
  "entityType": "ENTITY_TYPE_ACTOR"
}