{
  "entityType": "ENTITY_TYPE_ACTOR",
  "classType": "CLASS_TYPE_MONSTER",
  "level": 2,
  "abilities": {
    "strength": 14,
    "dexterity": 12,
    "constitution": 11,
    "intelligence": 6,
    "wisdom": 10,
    "charisma": 6
  },
  "size": "CREATURE_SIZE_MEDIUM",
  "specie": "SPECIE_HUMANOID",
  "equipment": [
    "wpn-spear",
    "wpn-longbow",
    "ammo-arrow",
    "arm-leather",
    {
      "entityType": "ENTITY_TYPE_ITEM",
      "itemType": "ITEM_TYPE_NATURAL_WEAPON",
      "damage": "1d4",
      "damageType": "DAMAGE_TYPE_WEAPON",
      "attributes": [],
      "properties": []
    }
  ],
  "actions": [
    "sla-natural-weapon-attack"
  ]
}