{
  "name": "c-cave-locust",
  "actions": [
    {
      "name": "bite",
      "count": 1,
      "amp": "1d2",
      "script": "damage",
      "data": {}
    },
    {
      "name": "bump",
      "count": 1,
      "amp": "1d4",
      "script": "damage",
      "data": {}
    },
    {
      "name": "spit",
      "count": 1,
      "amp": 0,
      "script": "spit",
      "data": {}
    }
  ],
  "saveAs": {
    "level": 2,
    "classType": "fighter"
  },
  "ac": 16,
  "properties": [],
  "specie": "vermin",
  "level": 2,
  "speed": 20
}