{
  "RACE_HUMAN": {
    "specie": "SPECIE_HUMANOID"
  },
  "RACE_ELF": {
    "specie": "SPECIE_HUMANOID",
    "abilityRestrictions": {
      "ABILITY_INTELLIGENCE": {
        "min": 9
      },
      "ABILITY_CONSTITUTION": {
        "max": 17
      }
    },
    "weaponRestrictions": {},
    "maxHdPerLevel": 6,
    "savingThrows": {
      "SAVING_THROW_PARALYSIS_PETRIFY": 1,
      "SAVING_THROW_MAGIC_WAND": 2,
      "SAVING_THROW_SPELL": 2
    },
    "properties": [
      {
        "property": "ITEM_PROPERTY_DARKVISION",
        "amp": 0,
        "data": {}
      },
      {
        "property": "ITEM_PROPERTY_IMMUNITY",
        "amp": 0,
        "data": {
          "immunityType": "IMMUNITY_TYPE_PARALYSIS"
        }
      }
    ]
  },
  "RACE_DWARF": {
    "specie": "SPECIE_HUMANOID",
    "abilityRestrictions": {
      "ABILITY_CONSTITUTION": {
        "min": 9
      },
      "ABILITY_CHARISMA": {
        "max": 17
      }
    },
    "weaponRestrictions": {
      "weaponSize": ["WEAPON_SIZE_SMALL", "WEAPON_SIZE_MEDIUM"]
    },
    "savingThrows": {
      "SAVING_THROW_DEATH_RAY_POISON": 4,
      "SAVING_THROW_PARALYSIS_PETRIFY": 4,
      "SAVING_THROW_MAGIC_WAND": 4,
      "SAVING_THROW_SPELL": 4,
      "SAVING_THROW_DRAGON_BREATH": 3
    },
    "properties": [
      {
        "property": "ITEM_PROPERTY_DARKVISION",
        "amp": 0,
        "data": {}
      }
    ]
  },
  "RACE_HALFLING": {
    "specie": "SPECIE_HUMANOID",
    "abilityRestrictions": {
      "ABILITY_DEXTERITY": {
        "min": 9
      },
      "ABILITY_STRENGTH": {
        "max": 17
      }
    },
    "weaponRestrictions": {
      "weaponSize": ["WEAPON_SIZE_SMALL"]
    },
    "maxHdPerLevel": 6,
    "savingThrows": {
      "SAVING_THROW_DEATH_RAY_POISON": 4,
      "SAVING_THROW_PARALYSIS_PETRIFY": 4,
      "SAVING_THROW_MAGIC_WAND": 4,
      "SAVING_THROW_SPELL": 4,
      "SAVING_THROW_DRAGON_BREATH": 3
    },
    "rogueSkills": {
      "SKILL_HIDE": 70
    },
    "properties": [
      {
        "property": "ITEM_PROPERTY_ATTACK_MODIFIER",
        "amp": 1,
        "data": {
          "attackType": "ATTACK_TYPE_RANGED"
        }
      },
      {
        "property": "ITEM_PROPERTY_ARMOR_CLASS_MODIFIER",
        "amp": 2,
        "data": {}
      }
    ]
  }
}